{"servc-api":{"label":"servc-api","status":"CU-86byr8p1e_UP---DisabledFrozen-Investors-Capital-Accounts-Visible-in-UP_Yulya-Zubareva deployed Thu Jun  6 14:11:14 UTC 2024","color":"0504cd"},"servc-api-demo-prod":{"label":"servc-api-demo-prod","status":"CU-86bxv8t4c_AP---Revise-User-Status-Logic-for-Admin-Invited-Users_Yulya-Zubareva deployed Thu Jun  6 13:45:49 UTC 2024","color":"CD0504"},"servc-api-prod":{"label":"servc-api-prod","status":"master deployed Wed Jun  5 19:40:20 UTC 2024","color":"04CD05"},"servc-app-production":{"label":"servc-app-production","status":"master deployed Wed Jun  5 19:39:56 UTC 2024","color":"04CD05"},"servc-admin-prod":{"label":"servc-admin-prod","status":"master deployed Wed Jun  5 19:40:44 UTC 2024","color":"04CD05"},"servc-app-demo-prod":{"label":"servc-app-demo-prod","status":"demo deployed Wed Jun  5 18:11:51 UTC 2024","color":"CD0504"},"servc-admin":{"label":"servc-admin","status":"master deployed Wed Jun  5 13:47:26 UTC 2024","color":"0504cd"},"servc-app":{"label":"servc-app","status":"CU-86byr8p1e_UP---DisabledFrozen-Investors-Capital-Accounts-Visible-in-UP_Yulya-Zubareva deployed Thu Jun  6 11:49:19 UTC 2024","color":"0504cd"},"servc-admin-demo-prod":{"label":"servc-admin-demo-prod","status":"CU-86bxv8t4c_AP---Revise-User-Status-Logic-for-Admin-Invited-Users_Yulya-Zubareva deployed Thu Jun  6 08:26:40 UTC 2024","color":"CD0504"}}